yta_audio_narration_open_voice/__init__.py
yta_audio_narration_open_voice-0.0.2.dist-info/LICENSE
yta_audio_narration_open_voice-0.0.2.dist-info/METADATA
yta_audio_narration_open_voice-0.0.2.dist-info/WHEEL
yta_audio_narration_open_voice-0.0.2.dist-info/RECORD
